py_omaha/__init__.py
py_omaha/py_omaha.py
py_omaha-0.1.0.dist-info/METADATA
py_omaha-0.1.0.dist-info/WHEEL
py_omaha-0.1.0.dist-info/top_level.txt
py_omaha-0.1.0.dist-info/RECORD
