Metadata-Version: 2.1
Name: py-omaha
Version: 0.1.0
Summary: A Python library to interact with the TP-Link Omaha Wifi Access Point management system
Home-page: UNKNOWN
Author: Ilaria Schinina <ilaria@schinina.eu>
Author-email: UNKNOWN
License: MIT
Platform: UNKNOWN
Requires-Dist: requests (>=2.17.0)
